{
  "a_comp_cor_00": {
    "CumulativeVarianceExplained": 0.0585521367,
    "Mask": "combined",
    "Method": "aCompCor",
    "Retained": true,
    "SingularValue": 96.1833540266,
    "VarianceExplained": 0.0585521367
  },
  "a_comp_cor_01": {
    "CumulativeVarianceExplained": 0.0890662273,
    "Mask": "combined",
    "Method": "aCompCor",
    "Retained": true,
    "SingularValue": 69.4350511557,
    "VarianceExplained": 0.0305140907
  },
  "a_comp_cor_02": {
    "CumulativeVarianceExplained": 0.1101033527,
    "Mask": "combined",
    "Method": "aCompCor",
    "Retained": true,
    "SingularValue": 57.6529774097,
    "VarianceExplained": 0.0210371253
  },
  "a_comp_cor_03": {
    "CumulativeVarianceExplained": 0.1289578406,
    "Mask": "combined",
    "Method": "aCompCor",
    "Retained": true,
    "SingularValue": 54.5802995,
    "VarianceExplained": 0.0188544879
  },
  "a_comp_cor_04": {
    "CumulativeVarianceExplained": 0.1432454378,
    "Mask": "combined",
    "Method": "aCompCor",
    "Retained": true,
    "SingularValue": 47.5125283593,
    "VarianceExplained": 0.0142875972
  },
  "a_comp_cor_05": {
    "CumulativeVarianceExplained": 0.1564059097,
    "Mask": "combined",
    "Method": "aCompCor",
    "Retained": true,
    "SingularValue": 45.5999403118,
    "VarianceExplained": 0.0131604719
  },
  "a_comp_cor_06": {
    "CumulativeVarianceExplained": 0.1671795777,
    "Mask": "combined",
    "Method": "aCompCor",
    "Retained": true,
    "SingularValue": 41.2582058154,
    "VarianceExplained": 0.010773668
  },
  "a_comp_cor_07": {
    "CumulativeVarianceExplained": 0.1774925047,
    "Mask": "combined",
    "Method": "aCompCor",
    "Retained": true,
    "SingularValue": 40.3663531205,
    "VarianceExplained": 0.010312927
  },
  "a_comp_cor_08": {
    "CumulativeVarianceExplained": 0.1877864079,
    "Mask": "combined",
    "Method": "aCompCor",
    "Retained": true,
    "SingularValue": 40.3291050965,
    "VarianceExplained": 0.0102939033
  },
  "a_comp_cor_09": {
    "CumulativeVarianceExplained": 0.1978574208,
    "Mask": "combined",
    "Method": "aCompCor",
    "Retained": true,
    "SingularValue": 39.8900994248,
    "VarianceExplained": 0.0100710129
  },
  "a_comp_cor_10": {
    "CumulativeVarianceExplained": 0.2075508866,
    "Mask": "combined",
    "Method": "aCompCor",
    "Retained": true,
    "SingularValue": 39.1352475079,
    "VarianceExplained": 0.0096934658
  },
  "a_comp_cor_11": {
    "CumulativeVarianceExplained": 0.2169595745,
    "Mask": "combined",
    "Method": "aCompCor",
    "Retained": true,
    "SingularValue": 38.556097912,
    "VarianceExplained": 0.0094086879
  },
  "a_comp_cor_12": {
    "CumulativeVarianceExplained": 0.2262945276,
    "Mask": "combined",
    "Method": "aCompCor",
    "Retained": true,
    "SingularValue": 38.404720849,
    "VarianceExplained": 0.0093349531
  },
  "a_comp_cor_13": {
    "CumulativeVarianceExplained": 0.2355053496,
    "Mask": "combined",
    "Method": "aCompCor",
    "Retained": true,
    "SingularValue": 38.148523962,
    "VarianceExplained": 0.009210822
  },
  "a_comp_cor_14": {
    "CumulativeVarianceExplained": 0.2446886517,
    "Mask": "combined",
    "Method": "aCompCor",
    "Retained": true,
    "SingularValue": 38.0914915733,
    "VarianceExplained": 0.0091833021
  },
  "a_comp_cor_15": {
    "CumulativeVarianceExplained": 0.2537298604,
    "Mask": "combined",
    "Method": "aCompCor",
    "Retained": true,
    "SingularValue": 37.7956475431,
    "VarianceExplained": 0.0090412087
  },
  "a_comp_cor_16": {
    "CumulativeVarianceExplained": 0.2625245462,
    "Mask": "combined",
    "Method": "aCompCor",
    "Retained": true,
    "SingularValue": 37.2768073229,
    "VarianceExplained": 0.0087946858
  },
  "a_comp_cor_17": {
    "CumulativeVarianceExplained": 0.271274339,
    "Mask": "combined",
    "Method": "aCompCor",
    "Retained": true,
    "SingularValue": 37.181544699,
    "VarianceExplained": 0.0087497928
  },
  "a_comp_cor_18": {
    "CumulativeVarianceExplained": 0.2798910053,
    "Mask": "combined",
    "Method": "aCompCor",
    "Retained": true,
    "SingularValue": 36.8976051139,
    "VarianceExplained": 0.0086166662
  },
  "a_comp_cor_19": {
    "CumulativeVarianceExplained": 0.2884500384,
    "Mask": "combined",
    "Method": "aCompCor",
    "Retained": true,
    "SingularValue": 36.7740022585,
    "VarianceExplained": 0.0085590332
  },
  "a_comp_cor_20": {
    "CumulativeVarianceExplained": 0.2969273201,
    "Mask": "combined",
    "Method": "aCompCor",
    "Retained": true,
    "SingularValue": 36.597957529,
    "VarianceExplained": 0.0084772816
  },
  "a_comp_cor_21": {
    "CumulativeVarianceExplained": 0.3052896695,
    "Mask": "combined",
    "Method": "aCompCor",
    "Retained": true,
    "SingularValue": 36.3490193792,
    "VarianceExplained": 0.0083623494
  },
  "a_comp_cor_22": {
    "CumulativeVarianceExplained": 0.3135617128,
    "Mask": "combined",
    "Method": "aCompCor",
    "Retained": true,
    "SingularValue": 36.1522176493,
    "VarianceExplained": 0.0082720433
  },
  "a_comp_cor_23": {
    "CumulativeVarianceExplained": 0.3216353346,
    "Mask": "combined",
    "Method": "aCompCor",
    "Retained": true,
    "SingularValue": 35.7159941712,
    "VarianceExplained": 0.0080736218
  },
  "a_comp_cor_24": {
    "CumulativeVarianceExplained": 0.3296770825,
    "Mask": "combined",
    "Method": "aCompCor",
    "Retained": true,
    "SingularValue": 35.6454229997,
    "VarianceExplained": 0.008041748
  },
  "a_comp_cor_25": {
    "CumulativeVarianceExplained": 0.3377120438,
    "Mask": "combined",
    "Method": "aCompCor",
    "Retained": true,
    "SingularValue": 35.6303786616,
    "VarianceExplained": 0.0080349613
  },
  "a_comp_cor_26": {
    "CumulativeVarianceExplained": 0.3455926944,
    "Mask": "combined",
    "Method": "aCompCor",
    "Retained": true,
    "SingularValue": 35.2865808683,
    "VarianceExplained": 0.0078806506
  },
  "a_comp_cor_27": {
    "CumulativeVarianceExplained": 0.3534091833,
    "Mask": "combined",
    "Method": "aCompCor",
    "Retained": true,
    "SingularValue": 35.1426414413,
    "VarianceExplained": 0.0078164889
  },
  "a_comp_cor_28": {
    "CumulativeVarianceExplained": 0.3611429706,
    "Mask": "combined",
    "Method": "aCompCor",
    "Retained": true,
    "SingularValue": 34.9562353259,
    "VarianceExplained": 0.0077337873
  },
  "a_comp_cor_29": {
    "CumulativeVarianceExplained": 0.3687805677,
    "Mask": "combined",
    "Method": "aCompCor",
    "Retained": true,
    "SingularValue": 34.7381684359,
    "VarianceExplained": 0.0076375971
  },
  "a_comp_cor_30": {
    "CumulativeVarianceExplained": 0.3763933965,
    "Mask": "combined",
    "Method": "aCompCor",
    "Retained": true,
    "SingularValue": 34.6817956444,
    "VarianceExplained": 0.0076128288
  },
  "a_comp_cor_31": {
    "CumulativeVarianceExplained": 0.3839064192,
    "Mask": "combined",
    "Method": "aCompCor",
    "Retained": true,
    "SingularValue": 34.4537021281,
    "VarianceExplained": 0.0075130227
  },
  "a_comp_cor_32": {
    "CumulativeVarianceExplained": 0.3913701442,
    "Mask": "combined",
    "Method": "aCompCor",
    "Retained": true,
    "SingularValue": 34.3404796297,
    "VarianceExplained": 0.0074637249
  },
  "a_comp_cor_33": {
    "CumulativeVarianceExplained": 0.3987794697,
    "Mask": "combined",
    "Method": "aCompCor",
    "Retained": true,
    "SingularValue": 34.2151054457,
    "VarianceExplained": 0.0074093256
  },
  "a_comp_cor_34": {
    "CumulativeVarianceExplained": 0.406110554,
    "Mask": "combined",
    "Method": "aCompCor",
    "Retained": true,
    "SingularValue": 34.0339729687,
    "VarianceExplained": 0.0073310843
  },
  "a_comp_cor_35": {
    "CumulativeVarianceExplained": 0.413371945,
    "Mask": "combined",
    "Method": "aCompCor",
    "Retained": true,
    "SingularValue": 33.8718137864,
    "VarianceExplained": 0.0072613909
  },
  "a_comp_cor_36": {
    "CumulativeVarianceExplained": 0.4204670008,
    "Mask": "combined",
    "Method": "aCompCor",
    "Retained": true,
    "SingularValue": 33.4816192473,
    "VarianceExplained": 0.0070950559
  },
  "a_comp_cor_37": {
    "CumulativeVarianceExplained": 0.4274884688,
    "Mask": "combined",
    "Method": "aCompCor",
    "Retained": true,
    "SingularValue": 33.3075358964,
    "VarianceExplained": 0.007021468
  },
  "a_comp_cor_38": {
    "CumulativeVarianceExplained": 0.4344796455,
    "Mask": "combined",
    "Method": "aCompCor",
    "Retained": true,
    "SingularValue": 33.2356120828,
    "VarianceExplained": 0.0069911766
  },
  "a_comp_cor_39": {
    "CumulativeVarianceExplained": 0.4414293129,
    "Mask": "combined",
    "Method": "aCompCor",
    "Retained": true,
    "SingularValue": 33.1367990596,
    "VarianceExplained": 0.0069496674
  },
  "a_comp_cor_40": {
    "CumulativeVarianceExplained": 0.4483705725,
    "Mask": "combined",
    "Method": "aCompCor",
    "Retained": true,
    "SingularValue": 33.1167482042,
    "VarianceExplained": 0.0069412596
  },
  "a_comp_cor_41": {
    "CumulativeVarianceExplained": 0.4552277266,
    "Mask": "combined",
    "Method": "aCompCor",
    "Retained": true,
    "SingularValue": 32.9155031663,
    "VarianceExplained": 0.0068571541
  },
  "a_comp_cor_42": {
    "CumulativeVarianceExplained": 0.4619579453,
    "Mask": "combined",
    "Method": "aCompCor",
    "Retained": true,
    "SingularValue": 32.6094243638,
    "VarianceExplained": 0.0067302187
  },
  "a_comp_cor_43": {
    "CumulativeVarianceExplained": 0.4686673896,
    "Mask": "combined",
    "Method": "aCompCor",
    "Retained": true,
    "SingularValue": 32.559057055,
    "VarianceExplained": 0.0067094443
  },
  "a_comp_cor_44": {
    "CumulativeVarianceExplained": 0.4752483982,
    "Mask": "combined",
    "Method": "aCompCor",
    "Retained": true,
    "SingularValue": 32.2459202015,
    "VarianceExplained": 0.0065810087
  },
  "a_comp_cor_45": {
    "CumulativeVarianceExplained": 0.4817462482,
    "Mask": "combined",
    "Method": "aCompCor",
    "Retained": true,
    "SingularValue": 32.0415400905,
    "VarianceExplained": 0.0064978499
  },
  "a_comp_cor_46": {
    "CumulativeVarianceExplained": 0.4881946834,
    "Mask": "combined",
    "Method": "aCompCor",
    "Retained": true,
    "SingularValue": 31.9194732114,
    "VarianceExplained": 0.0064484353
  },
  "a_comp_cor_47": {
    "CumulativeVarianceExplained": 0.4946101393,
    "Mask": "combined",
    "Method": "aCompCor",
    "Retained": true,
    "SingularValue": 31.8377453457,
    "VarianceExplained": 0.0064154559
  },
  "a_comp_cor_48": {
    "CumulativeVarianceExplained": 0.500960023,
    "Mask": "combined",
    "Method": "aCompCor",
    "Retained": true,
    "SingularValue": 31.6746210867,
    "VarianceExplained": 0.0063498837
  },
  "aroma_motion_1": {
    "CSFFraction": 0.03,
    "EdgeFraction": 0.63,
    "HighFrequencyContent": 0.07,
    "MaximumRpCorrelation": 0.91,
    "Method": {
      "Name": "ICA-AROMA",
      "Version": "0.4.5"
    },
    "ModelVarianceExplained": 0.0697286255,
    "MotionNoise": true,
    "TotalVarianceExplained": 0.0399688446
  },
  "aroma_motion_10": {
    "CSFFraction": 0.07,
    "EdgeFraction": 0.64,
    "HighFrequencyContent": 0.72,
    "MaximumRpCorrelation": 0.63,
    "Method": {
      "Name": "ICA-AROMA",
      "Version": "0.4.5"
    },
    "ModelVarianceExplained": 0.0382558163,
    "MotionNoise": true,
    "TotalVarianceExplained": 0.0219284514
  },
  "aroma_motion_11": {
    "CSFFraction": 0.02,
    "EdgeFraction": 0.59,
    "HighFrequencyContent": 0.15,
    "MaximumRpCorrelation": 0.16,
    "Method": {
      "Name": "ICA-AROMA",
      "Version": "0.4.5"
    },
    "ModelVarianceExplained": 0.0378693849,
    "MotionNoise": false,
    "TotalVarianceExplained": 0.0217069468
  },
  "aroma_motion_12": {
    "CSFFraction": 0.0,
    "EdgeFraction": 0.35,
    "HighFrequencyContent": 0.22,
    "MaximumRpCorrelation": 0.2,
    "Method": {
      "Name": "ICA-AROMA",
      "Version": "0.4.5"
    },
    "ModelVarianceExplained": 0.0377392068,
    "MotionNoise": false,
    "TotalVarianceExplained": 0.0216323279
  },
  "aroma_motion_13": {
    "CSFFraction": 0.02,
    "EdgeFraction": 0.52,
    "HighFrequencyContent": 0.17,
    "MaximumRpCorrelation": 0.33,
    "Method": {
      "Name": "ICA-AROMA",
      "Version": "0.4.5"
    },
    "ModelVarianceExplained": 0.0365835183,
    "MotionNoise": false,
    "TotalVarianceExplained": 0.0209698807
  },
  "aroma_motion_14": {
    "CSFFraction": 0.16,
    "EdgeFraction": 0.62,
    "HighFrequencyContent": 0.65,
    "MaximumRpCorrelation": 0.48,
    "Method": {
      "Name": "ICA-AROMA",
      "Version": "0.4.5"
    },
    "ModelVarianceExplained": 0.0359270731,
    "MotionNoise": true,
    "TotalVarianceExplained": 0.0205936026
  },
  "aroma_motion_15": {
    "CSFFraction": 0.13,
    "EdgeFraction": 0.32,
    "HighFrequencyContent": 0.45,
    "MaximumRpCorrelation": 0.33,
    "Method": {
      "Name": "ICA-AROMA",
      "Version": "0.4.5"
    },
    "ModelVarianceExplained": 0.0358765173,
    "MotionNoise": true,
    "TotalVarianceExplained": 0.0205646237
  },
  "aroma_motion_16": {
    "CSFFraction": 0.02,
    "EdgeFraction": 0.46,
    "HighFrequencyContent": 0.15,
    "MaximumRpCorrelation": 0.47,
    "Method": {
      "Name": "ICA-AROMA",
      "Version": "0.4.5"
    },
    "ModelVarianceExplained": 0.0350966921,
    "MotionNoise": false,
    "TotalVarianceExplained": 0.0201176235
  },
  "aroma_motion_17": {
    "CSFFraction": 0.17,
    "EdgeFraction": 0.44,
    "HighFrequencyContent": 0.34,
    "MaximumRpCorrelation": 0.29,
    "Method": {
      "Name": "ICA-AROMA",
      "Version": "0.4.5"
    },
    "ModelVarianceExplained": 0.0345314712,
    "MotionNoise": true,
    "TotalVarianceExplained": 0.0197936356
  },
  "aroma_motion_18": {
    "CSFFraction": 0.06,
    "EdgeFraction": 0.45,
    "HighFrequencyContent": 0.41,
    "MaximumRpCorrelation": 0.3,
    "Method": {
      "Name": "ICA-AROMA",
      "Version": "0.4.5"
    },
    "ModelVarianceExplained": 0.0344793245,
    "MotionNoise": true,
    "TotalVarianceExplained": 0.0197637449
  },
  "aroma_motion_19": {
    "CSFFraction": 0.03,
    "EdgeFraction": 0.41,
    "HighFrequencyContent": 0.24,
    "MaximumRpCorrelation": 0.49,
    "Method": {
      "Name": "ICA-AROMA",
      "Version": "0.4.5"
    },
    "ModelVarianceExplained": 0.0340927405,
    "MotionNoise": false,
    "TotalVarianceExplained": 0.0195421527
  },
  "aroma_motion_2": {
    "CSFFraction": 0.27,
    "EdgeFraction": 0.66,
    "HighFrequencyContent": 0.4,
    "MaximumRpCorrelation": 0.4,
    "Method": {
      "Name": "ICA-AROMA",
      "Version": "0.4.5"
    },
    "ModelVarianceExplained": 0.0620264128,
    "MotionNoise": true,
    "TotalVarianceExplained": 0.0355538925
  },
  "aroma_motion_20": {
    "CSFFraction": 0.16,
    "EdgeFraction": 0.6,
    "HighFrequencyContent": 0.44,
    "MaximumRpCorrelation": 0.4,
    "Method": {
      "Name": "ICA-AROMA",
      "Version": "0.4.5"
    },
    "ModelVarianceExplained": 0.0339594734,
    "MotionNoise": true,
    "TotalVarianceExplained": 0.0194657632
  },
  "aroma_motion_21": {
    "CSFFraction": 0.08,
    "EdgeFraction": 0.72,
    "HighFrequencyContent": 0.34,
    "MaximumRpCorrelation": 0.3,
    "Method": {
      "Name": "ICA-AROMA",
      "Version": "0.4.5"
    },
    "ModelVarianceExplained": 0.0336643891,
    "MotionNoise": true,
    "TotalVarianceExplained": 0.0192966193
  },
  "aroma_motion_22": {
    "CSFFraction": 0.02,
    "EdgeFraction": 0.35,
    "HighFrequencyContent": 0.14,
    "MaximumRpCorrelation": 0.3,
    "Method": {
      "Name": "ICA-AROMA",
      "Version": "0.4.5"
    },
    "ModelVarianceExplained": 0.0334138038,
    "MotionNoise": false,
    "TotalVarianceExplained": 0.0191529823
  },
  "aroma_motion_23": {
    "CSFFraction": 0.02,
    "EdgeFraction": 0.33,
    "HighFrequencyContent": 0.21,
    "MaximumRpCorrelation": 0.45,
    "Method": {
      "Name": "ICA-AROMA",
      "Version": "0.4.5"
    },
    "ModelVarianceExplained": 0.0329409773,
    "MotionNoise": false,
    "TotalVarianceExplained": 0.0188819555
  },
  "aroma_motion_24": {
    "CSFFraction": 0.07,
    "EdgeFraction": 0.46,
    "HighFrequencyContent": 0.31,
    "MaximumRpCorrelation": 0.28,
    "Method": {
      "Name": "ICA-AROMA",
      "Version": "0.4.5"
    },
    "ModelVarianceExplained": 0.0293342759,
    "MotionNoise": false,
    "TotalVarianceExplained": 0.0168145737
  },
  "aroma_motion_25": {
    "CSFFraction": 0.02,
    "EdgeFraction": 0.44,
    "HighFrequencyContent": 0.18,
    "MaximumRpCorrelation": 0.44,
    "Method": {
      "Name": "ICA-AROMA",
      "Version": "0.4.5"
    },
    "ModelVarianceExplained": 0.0289306102,
    "MotionNoise": false,
    "TotalVarianceExplained": 0.0165831903
  },
  "aroma_motion_3": {
    "CSFFraction": 0.01,
    "EdgeFraction": 0.57,
    "HighFrequencyContent": 0.25,
    "MaximumRpCorrelation": 0.94,
    "Method": {
      "Name": "ICA-AROMA",
      "Version": "0.4.5"
    },
    "ModelVarianceExplained": 0.0558628383,
    "MotionNoise": true,
    "TotalVarianceExplained": 0.0320208966
  },
  "aroma_motion_4": {
    "CSFFraction": 0.11,
    "EdgeFraction": 0.45,
    "HighFrequencyContent": 0.29,
    "MaximumRpCorrelation": 0.6,
    "Method": {
      "Name": "ICA-AROMA",
      "Version": "0.4.5"
    },
    "ModelVarianceExplained": 0.04940931,
    "MotionNoise": true,
    "TotalVarianceExplained": 0.0283216974
  },
  "aroma_motion_5": {
    "CSFFraction": 0.07,
    "EdgeFraction": 0.4,
    "HighFrequencyContent": 0.38,
    "MaximumRpCorrelation": 0.47,
    "Method": {
      "Name": "ICA-AROMA",
      "Version": "0.4.5"
    },
    "ModelVarianceExplained": 0.0457831309,
    "MotionNoise": true,
    "TotalVarianceExplained": 0.026243151
  },
  "aroma_motion_6": {
    "CSFFraction": 0.3,
    "EdgeFraction": 0.67,
    "HighFrequencyContent": 0.39,
    "MaximumRpCorrelation": 0.32,
    "Method": {
      "Name": "ICA-AROMA",
      "Version": "0.4.5"
    },
    "ModelVarianceExplained": 0.0426691028,
    "MotionNoise": true,
    "TotalVarianceExplained": 0.0244581723
  },
  "aroma_motion_7": {
    "CSFFraction": 0.22,
    "EdgeFraction": 0.61,
    "HighFrequencyContent": 0.33,
    "MaximumRpCorrelation": 0.4,
    "Method": {
      "Name": "ICA-AROMA",
      "Version": "0.4.5"
    },
    "ModelVarianceExplained": 0.0412632909,
    "MotionNoise": true,
    "TotalVarianceExplained": 0.023652353
  },
  "aroma_motion_8": {
    "CSFFraction": 0.09,
    "EdgeFraction": 0.43,
    "HighFrequencyContent": 0.4,
    "MaximumRpCorrelation": 0.36,
    "Method": {
      "Name": "ICA-AROMA",
      "Version": "0.4.5"
    },
    "ModelVarianceExplained": 0.0410629384,
    "MotionNoise": true,
    "TotalVarianceExplained": 0.0235375098
  },
  "aroma_motion_9": {
    "CSFFraction": 0.01,
    "EdgeFraction": 0.5,
    "HighFrequencyContent": 0.11,
    "MaximumRpCorrelation": 0.37,
    "Method": {
      "Name": "ICA-AROMA",
      "Version": "0.4.5"
    },
    "ModelVarianceExplained": 0.0394990757,
    "MotionNoise": false,
    "TotalVarianceExplained": 0.0226410948
  },
  "c_comp_cor_00": {
    "CumulativeVarianceExplained": 0.1706372047,
    "Mask": "CSF",
    "Method": "aCompCor",
    "Retained": true,
    "SingularValue": 77.5011587356,
    "VarianceExplained": 0.1706372047
  },
  "c_comp_cor_01": {
    "CumulativeVarianceExplained": 0.299252247,
    "Mask": "CSF",
    "Method": "aCompCor",
    "Retained": true,
    "SingularValue": 67.2848384705,
    "VarianceExplained": 0.1286150423
  },
  "c_comp_cor_02": {
    "CumulativeVarianceExplained": 0.3593258421,
    "Mask": "CSF",
    "Method": "aCompCor",
    "Retained": true,
    "SingularValue": 45.9846773188,
    "VarianceExplained": 0.0600735951
  },
  "c_comp_cor_03": {
    "CumulativeVarianceExplained": 0.4104671651,
    "Mask": "CSF",
    "Method": "aCompCor",
    "Retained": true,
    "SingularValue": 42.4284641345,
    "VarianceExplained": 0.051141323
  },
  "c_comp_cor_04": {
    "CumulativeVarianceExplained": 0.4448354891,
    "Mask": "CSF",
    "Method": "aCompCor",
    "Retained": true,
    "SingularValue": 34.7816763075,
    "VarianceExplained": 0.0343683241
  },
  "c_comp_cor_05": {
    "CumulativeVarianceExplained": 0.4728322346,
    "Mask": "CSF",
    "Method": "aCompCor",
    "Retained": true,
    "SingularValue": 31.392442409,
    "VarianceExplained": 0.0279967455
  },
  "c_comp_cor_06": {
    "CumulativeVarianceExplained": 0.4997319035,
    "Mask": "CSF",
    "Method": "aCompCor",
    "Retained": true,
    "SingularValue": 30.7712259348,
    "VarianceExplained": 0.0268996689
  },
  "c_comp_cor_07": {
    "CumulativeVarianceExplained": 0.5197841459,
    "Mask": "CSF",
    "Method": "aCompCor",
    "Retained": true,
    "SingularValue": 26.5676294446,
    "VarianceExplained": 0.0200522425
  },
  "csf": {
    "Method": "Mean"
  },
  "csf_wm": {
    "Method": "Mean"
  },
  "global_signal": {
    "Method": "Mean"
  },
  "t_comp_cor_00": {
    "CumulativeVarianceExplained": 0.271898646,
    "Method": "tCompCor",
    "Retained": true,
    "SingularValue": 158.5037377945,
    "VarianceExplained": 0.271898646
  },
  "t_comp_cor_01": {
    "CumulativeVarianceExplained": 0.5006808315,
    "Method": "tCompCor",
    "Retained": true,
    "SingularValue": 145.3942018675,
    "VarianceExplained": 0.2287821855
  },
  "tcompcor": {
    "Method": "Mean"
  },
  "w_comp_cor_00": {
    "CumulativeVarianceExplained": 0.0175406099,
    "Mask": "WM",
    "Method": "aCompCor",
    "Retained": true,
    "SingularValue": 40.8210478122,
    "VarianceExplained": 0.0175406099
  },
  "w_comp_cor_01": {
    "CumulativeVarianceExplained": 0.0338555703,
    "Mask": "WM",
    "Method": "aCompCor",
    "Retained": true,
    "SingularValue": 39.3690390602,
    "VarianceExplained": 0.0163149604
  },
  "w_comp_cor_02": {
    "CumulativeVarianceExplained": 0.0493958816,
    "Mask": "WM",
    "Method": "aCompCor",
    "Retained": true,
    "SingularValue": 38.4230344404,
    "VarianceExplained": 0.0155403113
  },
  "w_comp_cor_03": {
    "CumulativeVarianceExplained": 0.0628480454,
    "Mask": "WM",
    "Method": "aCompCor",
    "Retained": true,
    "SingularValue": 35.7485042111,
    "VarianceExplained": 0.0134521637
  },
  "w_comp_cor_04": {
    "CumulativeVarianceExplained": 0.0760116062,
    "Mask": "WM",
    "Method": "aCompCor",
    "Retained": true,
    "SingularValue": 35.3629505965,
    "VarianceExplained": 0.0131635608
  },
  "w_comp_cor_05": {
    "CumulativeVarianceExplained": 0.088886313,
    "Mask": "WM",
    "Method": "aCompCor",
    "Retained": true,
    "SingularValue": 34.9728058475,
    "VarianceExplained": 0.0128747068
  },
  "w_comp_cor_06": {
    "CumulativeVarianceExplained": 0.1013832438,
    "Mask": "WM",
    "Method": "aCompCor",
    "Retained": true,
    "SingularValue": 34.4558911012,
    "VarianceExplained": 0.0124969309
  },
  "w_comp_cor_07": {
    "CumulativeVarianceExplained": 0.1137147783,
    "Mask": "WM",
    "Method": "aCompCor",
    "Retained": true,
    "SingularValue": 34.2271204603,
    "VarianceExplained": 0.0123315345
  },
  "w_comp_cor_08": {
    "CumulativeVarianceExplained": 0.1258403214,
    "Mask": "WM",
    "Method": "aCompCor",
    "Retained": true,
    "SingularValue": 33.9400440318,
    "VarianceExplained": 0.012125543
  },
  "w_comp_cor_09": {
    "CumulativeVarianceExplained": 0.1378599083,
    "Mask": "WM",
    "Method": "aCompCor",
    "Retained": true,
    "SingularValue": 33.791430279,
    "VarianceExplained": 0.012019587
  },
  "w_comp_cor_10": {
    "CumulativeVarianceExplained": 0.1496643561,
    "Mask": "WM",
    "Method": "aCompCor",
    "Retained": true,
    "SingularValue": 33.4876476068,
    "VarianceExplained": 0.0118044478
  },
  "w_comp_cor_11": {
    "CumulativeVarianceExplained": 0.1613594431,
    "Mask": "WM",
    "Method": "aCompCor",
    "Retained": true,
    "SingularValue": 33.3321655393,
    "VarianceExplained": 0.0116950869
  },
  "w_comp_cor_12": {
    "CumulativeVarianceExplained": 0.172642723,
    "Mask": "WM",
    "Method": "aCompCor",
    "Retained": true,
    "SingularValue": 32.740061013,
    "VarianceExplained": 0.0112832799
  },
  "w_comp_cor_13": {
    "CumulativeVarianceExplained": 0.1838450746,
    "Mask": "WM",
    "Method": "aCompCor",
    "Retained": true,
    "SingularValue": 32.6224370899,
    "VarianceExplained": 0.0112023516
  },
  "w_comp_cor_14": {
    "CumulativeVarianceExplained": 0.1947569752,
    "Mask": "WM",
    "Method": "aCompCor",
    "Retained": true,
    "SingularValue": 32.1967476004,
    "VarianceExplained": 0.0109119006
  },
  "w_comp_cor_15": {
    "CumulativeVarianceExplained": 0.2055466763,
    "Mask": "WM",
    "Method": "aCompCor",
    "Retained": true,
    "SingularValue": 32.0159586391,
    "VarianceExplained": 0.0107897011
  },
  "w_comp_cor_16": {
    "CumulativeVarianceExplained": 0.2161637698,
    "Mask": "WM",
    "Method": "aCompCor",
    "Retained": true,
    "SingularValue": 31.7588393925,
    "VarianceExplained": 0.0106170935
  },
  "w_comp_cor_17": {
    "CumulativeVarianceExplained": 0.2266504398,
    "Mask": "WM",
    "Method": "aCompCor",
    "Retained": true,
    "SingularValue": 31.5631691244,
    "VarianceExplained": 0.0104866699
  },
  "w_comp_cor_18": {
    "CumulativeVarianceExplained": 0.2369970867,
    "Mask": "WM",
    "Method": "aCompCor",
    "Retained": true,
    "SingularValue": 31.3517377216,
    "VarianceExplained": 0.0103466469
  },
  "w_comp_cor_19": {
    "CumulativeVarianceExplained": 0.2472670216,
    "Mask": "WM",
    "Method": "aCompCor",
    "Retained": true,
    "SingularValue": 31.2352976713,
    "VarianceExplained": 0.010269935
  },
  "w_comp_cor_20": {
    "CumulativeVarianceExplained": 0.2573959852,
    "Mask": "WM",
    "Method": "aCompCor",
    "Retained": true,
    "SingularValue": 31.020179539,
    "VarianceExplained": 0.0101289636
  },
  "w_comp_cor_21": {
    "CumulativeVarianceExplained": 0.2674197834,
    "Mask": "WM",
    "Method": "aCompCor",
    "Retained": true,
    "SingularValue": 30.8587237561,
    "VarianceExplained": 0.0100237982
  },
  "w_comp_cor_22": {
    "CumulativeVarianceExplained": 0.2773590379,
    "Mask": "WM",
    "Method": "aCompCor",
    "Retained": true,
    "SingularValue": 30.728312202,
    "VarianceExplained": 0.0099392544
  },
  "w_comp_cor_23": {
    "CumulativeVarianceExplained": 0.2871174964,
    "Mask": "WM",
    "Method": "aCompCor",
    "Retained": true,
    "SingularValue": 30.4475543237,
    "VarianceExplained": 0.0097584586
  },
  "w_comp_cor_24": {
    "CumulativeVarianceExplained": 0.2967415061,
    "Mask": "WM",
    "Method": "aCompCor",
    "Retained": true,
    "SingularValue": 30.2370785057,
    "VarianceExplained": 0.0096240096
  },
  "w_comp_cor_25": {
    "CumulativeVarianceExplained": 0.3062060213,
    "Mask": "WM",
    "Method": "aCompCor",
    "Retained": true,
    "SingularValue": 29.9854788683,
    "VarianceExplained": 0.0094645152
  },
  "w_comp_cor_26": {
    "CumulativeVarianceExplained": 0.3155254521,
    "Mask": "WM",
    "Method": "aCompCor",
    "Retained": true,
    "SingularValue": 29.7547632053,
    "VarianceExplained": 0.0093194309
  },
  "w_comp_cor_27": {
    "CumulativeVarianceExplained": 0.3247628789,
    "Mask": "WM",
    "Method": "aCompCor",
    "Retained": true,
    "SingularValue": 29.6235639648,
    "VarianceExplained": 0.0092374268
  },
  "w_comp_cor_28": {
    "CumulativeVarianceExplained": 0.3339038236,
    "Mask": "WM",
    "Method": "aCompCor",
    "Retained": true,
    "SingularValue": 29.4684534583,
    "VarianceExplained": 0.0091409447
  },
  "w_comp_cor_29": {
    "CumulativeVarianceExplained": 0.3429481464,
    "Mask": "WM",
    "Method": "aCompCor",
    "Retained": true,
    "SingularValue": 29.3122954709,
    "VarianceExplained": 0.0090443228
  },
  "w_comp_cor_30": {
    "CumulativeVarianceExplained": 0.3518896141,
    "Mask": "WM",
    "Method": "aCompCor",
    "Retained": true,
    "SingularValue": 29.1451441465,
    "VarianceExplained": 0.0089414677
  },
  "w_comp_cor_31": {
    "CumulativeVarianceExplained": 0.360769717,
    "Mask": "WM",
    "Method": "aCompCor",
    "Retained": true,
    "SingularValue": 29.0449613533,
    "VarianceExplained": 0.0088801029
  },
  "w_comp_cor_32": {
    "CumulativeVarianceExplained": 0.3695789638,
    "Mask": "WM",
    "Method": "aCompCor",
    "Retained": true,
    "SingularValue": 28.9288514501,
    "VarianceExplained": 0.0088092468
  },
  "w_comp_cor_33": {
    "CumulativeVarianceExplained": 0.3783047341,
    "Mask": "WM",
    "Method": "aCompCor",
    "Retained": true,
    "SingularValue": 28.7914601908,
    "VarianceExplained": 0.0087257703
  },
  "w_comp_cor_34": {
    "CumulativeVarianceExplained": 0.3868956862,
    "Mask": "WM",
    "Method": "aCompCor",
    "Retained": true,
    "SingularValue": 28.5681718778,
    "VarianceExplained": 0.008590952
  },
  "w_comp_cor_35": {
    "CumulativeVarianceExplained": 0.3954065896,
    "Mask": "WM",
    "Method": "aCompCor",
    "Retained": true,
    "SingularValue": 28.4347643162,
    "VarianceExplained": 0.0085109034
  },
  "w_comp_cor_36": {
    "CumulativeVarianceExplained": 0.4038304717,
    "Mask": "WM",
    "Method": "aCompCor",
    "Retained": true,
    "SingularValue": 28.2890226223,
    "VarianceExplained": 0.0084238821
  },
  "w_comp_cor_37": {
    "CumulativeVarianceExplained": 0.4121447488,
    "Mask": "WM",
    "Method": "aCompCor",
    "Retained": true,
    "SingularValue": 28.1043826609,
    "VarianceExplained": 0.0083142771
  },
  "w_comp_cor_38": {
    "CumulativeVarianceExplained": 0.420367674,
    "Mask": "WM",
    "Method": "aCompCor",
    "Retained": true,
    "SingularValue": 27.9495598687,
    "VarianceExplained": 0.0082229252
  },
  "w_comp_cor_39": {
    "CumulativeVarianceExplained": 0.428553677,
    "Mask": "WM",
    "Method": "aCompCor",
    "Retained": true,
    "SingularValue": 27.8867401767,
    "VarianceExplained": 0.0081860029
  },
  "w_comp_cor_40": {
    "CumulativeVarianceExplained": 0.4366541037,
    "Mask": "WM",
    "Method": "aCompCor",
    "Retained": true,
    "SingularValue": 27.7405937026,
    "VarianceExplained": 0.0081004267
  },
  "w_comp_cor_41": {
    "CumulativeVarianceExplained": 0.4445903237,
    "Mask": "WM",
    "Method": "aCompCor",
    "Retained": true,
    "SingularValue": 27.4579843768,
    "VarianceExplained": 0.0079362201
  },
  "w_comp_cor_42": {
    "CumulativeVarianceExplained": 0.4524264459,
    "Mask": "WM",
    "Method": "aCompCor",
    "Retained": true,
    "SingularValue": 27.2842739632,
    "VarianceExplained": 0.0078361222
  },
  "w_comp_cor_43": {
    "CumulativeVarianceExplained": 0.4602306565,
    "Mask": "WM",
    "Method": "aCompCor",
    "Retained": true,
    "SingularValue": 27.2286615212,
    "VarianceExplained": 0.0078042106
  },
  "w_comp_cor_44": {
    "CumulativeVarianceExplained": 0.4679243496,
    "Mask": "WM",
    "Method": "aCompCor",
    "Retained": true,
    "SingularValue": 27.0351778386,
    "VarianceExplained": 0.0076936931
  },
  "w_comp_cor_45": {
    "CumulativeVarianceExplained": 0.4755054428,
    "Mask": "WM",
    "Method": "aCompCor",
    "Retained": true,
    "SingularValue": 26.8366141669,
    "VarianceExplained": 0.0075810933
  },
  "w_comp_cor_46": {
    "CumulativeVarianceExplained": 0.4830422903,
    "Mask": "WM",
    "Method": "aCompCor",
    "Retained": true,
    "SingularValue": 26.7581857719,
    "VarianceExplained": 0.0075368474
  },
  "w_comp_cor_47": {
    "CumulativeVarianceExplained": 0.4904526781,
    "Mask": "WM",
    "Method": "aCompCor",
    "Retained": true,
    "SingularValue": 26.5327504445,
    "VarianceExplained": 0.0074103879
  },
  "w_comp_cor_48": {
    "CumulativeVarianceExplained": 0.4977948919,
    "Mask": "WM",
    "Method": "aCompCor",
    "Retained": true,
    "SingularValue": 26.41042048,
    "VarianceExplained": 0.0073422138
  },
  "w_comp_cor_49": {
    "CumulativeVarianceExplained": 0.5050121683,
    "Mask": "WM",
    "Method": "aCompCor",
    "Retained": true,
    "SingularValue": 26.1847523273,
    "VarianceExplained": 0.0072172764
  },
  "white_matter": {
    "Method": "Mean"
  }
}